priorityplot/__init__.py
priorityplot/__main__.py
priorityplot/main.py
priorityplot/model.py
priorityplot/plot_widget.py
priorityplot-0.1.2.dist-info/METADATA
priorityplot-0.1.2.dist-info/WHEEL
priorityplot-0.1.2.dist-info/entry_points.txt
priorityplot-0.1.2.dist-info/RECORD
