Metadata-Version: 2.4
Name: priorityplot
Version: 0.1.2
Summary: A priority plotting application with PyQt6
Project-URL: Homepage, https://github.com/cvujll/priorityplot
Project-URL: Repository, https://github.com/cvujll/priorityplot
Project-URL: Issues, https://github.com/cvujll/priorityplot/issues
Author-email: cvujll <cvujll@example.com>
License: MIT
Keywords: matplotlib,plotting,priority,pyqt6,visualization
Classifier: Development Status :: 3 - Alpha
Classifier: Intended Audience :: Developers
Classifier: License :: OSI Approved :: MIT License
Classifier: Programming Language :: Python :: 3
Classifier: Programming Language :: Python :: 3.8
Classifier: Programming Language :: Python :: 3.9
Classifier: Programming Language :: Python :: 3.10
Classifier: Programming Language :: Python :: 3.11
Classifier: Programming Language :: Python :: 3.12
Classifier: Topic :: Scientific/Engineering :: Visualization
Classifier: Topic :: Software Development :: Libraries :: Python Modules
Requires-Python: >=3.8
Requires-Dist: matplotlib
Requires-Dist: numpy
Requires-Dist: openpyxl
Requires-Dist: pyqt6
